<?xml version="1.0" encoding="utf-8"?>
<jack:Blackjack xmlns:jack="http://www.blackjack.com">
  <jack:Player Name="Player 1">
    <jack:Statistics>
      <jack:AverageAmountLost>-28.125</jack:AverageAmountLost>
      <jack:AverageAmountWon>30.681818181818183</jack:AverageAmountWon>
      <jack:Blackjacks>1</jack:Blackjacks>
      <jack:Losses>8</jack:Losses>
      <jack:NetAverageWinLoss>5.9210526315789478</jack:NetAverageWinLoss>
      <jack:NetWinLoss>112.5</jack:NetWinLoss>
      <jack:PercentageOfBlackJacks>0.041666666666666664</jack:PercentageOfBlackJacks>
      <jack:PercentageOfLosses>33.333333333333329</jack:PercentageOfLosses>
      <jack:PercentageOfPushes>16.666666666666664</jack:PercentageOfPushes>
      <jack:PercentageOfWins>45.833333333333329</jack:PercentageOfWins>
      <jack:Pushes>4</jack:Pushes>
      <jack:Surrenders>1</jack:Surrenders>
      <jack:TotalAmountLost>-225</jack:TotalAmountLost>
      <jack:TotalAmountWon>337.5</jack:TotalAmountWon>
      <jack:Wins>11</jack:Wins>
    </jack:Statistics>
  </jack:Player>
</jack:Blackjack>
